setup.py
pyscanning/__init__.py
pyscanning/pyscanning.py
pyscanning/wrapper.py
pyscanning.egg-info/PKG-INFO
pyscanning.egg-info/SOURCES.txt
pyscanning.egg-info/dependency_links.txt
pyscanning.egg-info/top_level.txt
pyscanning/backends/__init__.py
pyscanning/backends/_sane_.py
pyscanning/backends/_test_.py
pyscanning/backends/_twain_.py
pyscanning/backends/twain.pyd
pyscanning/testdata/__init__.py
pyscanning/testdata/img1.tiff
