Metadata-Version: 1.0
Name: pyscanning
Version: 0.2.1
Summary: A scanner wrapper for sane and twain.
Home-page: http://code.google.com/p/pyscanning
Author: Sergio Campos
Author-email: seocam@seocam.net
License: UNKNOWN
Platform: UNKNOWN
